LICENSE
MANIFEST.in
README.md
pyproject.toml
setup.py
dj_admin_2fa/__init__.py
dj_admin_2fa/admin.py
dj_admin_2fa/apps.py
dj_admin_2fa/forms.py
dj_admin_2fa/middleware.py
dj_admin_2fa/models.py
dj_admin_2fa/urls.py
dj_admin_2fa/utils.py
dj_admin_2fa/views.py
dj_admin_2fa.egg-info/PKG-INFO
dj_admin_2fa.egg-info/SOURCES.txt
dj_admin_2fa.egg-info/dependency_links.txt
dj_admin_2fa.egg-info/requires.txt
dj_admin_2fa.egg-info/top_level.txt
dj_admin_2fa/migrations/0001_initial.py
dj_admin_2fa/migrations/__init__.py
dj_admin_2fa/templates/admin_2fa_plus/backup_codes.html
dj_admin_2fa/templates/admin_2fa_plus/delete_device.html
dj_admin_2fa/templates/admin_2fa_plus/recovery.html
dj_admin_2fa/templates/admin_2fa_plus/setup.html
dj_admin_2fa/templates/admin_2fa_plus/verify.html
dj_admin_2fa/templates/admin_2fa_plus/verify_setup.html
tests/test_2fa_flow.py