Metadata-Version: 2.4
Name: dj-admin-2fa
Version: 1.0.0
Summary: Two-Factor Authentication for Django Admin with TOTP, backup codes, trusted devices, and more.
Home-page: https://github.com/SurajPysquad/dj-admin-2fa
Author: Suraj Patidar
Author-email: suraj.pysquad@gmail.com
License: MIT
Classifier: Framework :: Django
Classifier: Programming Language :: Python :: 3
Classifier: License :: OSI Approved :: MIT License
Classifier: Operating System :: OS Independent
Requires-Python: >=3.6
License-File: LICENSE
Requires-Dist: Django>=3.2
Requires-Dist: pyotp>=2.3.0
Requires-Dist: qrcode>=6.1
Requires-Dist: Pillow>=7.0
Dynamic: author
Dynamic: author-email
Dynamic: classifier
Dynamic: description
Dynamic: description-content-type
Dynamic: home-page
Dynamic: license
Dynamic: license-file
Dynamic: requires-dist
Dynamic: requires-python
Dynamic: summary
